{
    "Precommt4onecСценарии": {
        "ИспользоватьСценарииРепозитория": false,
        "КаталогЛокальныхСценариев": "",
        "ГлобальныеСценарии": [
            "ДобавлениеПробеловПередКлючевымиСловами.os",
            "ДобавлениеТестовВРасширение.os",
            "ЗапретИспользованияПерейти.os",
            "ИсправлениеНеКаноническогоНаписания.os",
            "КорректировкаXMLФорм.os",
            "ОбработкаЮнитТестов.os",
            "ОтключениеПолнотекстовогоПоиска.os",
            "ОтключениеРазрешенияИзменятьФорму.os",
            "ПроверкаДублейПроцедурИФункций.os",
            "ПроверкаКорректностиИнструкцийПрепроцессора.os",
            "ПроверкаКорректностиОбластей.os",
            "ПроверкаНецензурныхСлов.os",
            "РазборОбычныхФормНаИсходники.os",
            "РазборОтчетовОбработокРасширений.os",
            "СинхронизацияОбъектовМетаданныхИФайлов.os",
            "СортировкаДереваМетаданных.os",
            "СортировкаСоставаПодсистем.os",
            "УдалениеДублейМетаданных.os",
            "УдалениеЛишнихКонцевыхПробелов.os",
            "УдалениеЛишнихПустыхСтрок.os"
        ],
        "ОтключенныеСценарии": [],
        "НастройкиСценариев": {
            "ОтключениеПолнотекстовогоПоиска": {
                "МетаданныеДляИсключения": {
                    "src\\_example.xml": [
                        "Номер",
                        "ТабличнаяЧасть1.Реквизит"
                    ],
                    "src\\_example2.xml": []
                }
            },
            "ПроверкаНецензурныхСлов": {
                "ФайлСНецензурнымиСловами": "НецензурныеСлова.txt"
            },
            "РазборОтчетовОбработокРасширений": {
                "ИспользоватьНастройкиПоУмолчанию": true,
                "ВерсияПлатформы": ""
            },
            "СортировкаДереваМетаданных": {
                "УчитываяПрефикс": ""
            }
        }
    }
}